yfdata/__init__.py
yfdata/constants.py
yfdata/parsing.py
yfdata/provider.py
yfdata/urls.py
yfdata/utils.py
yfdata-0.1.7.dist-info/METADATA
yfdata-0.1.7.dist-info/WHEEL
yfdata-0.1.7.dist-info/licenses/LICENSE
yfdata-0.1.7.dist-info/RECORD
