Metadata-Version: 2.4
Name: yfdata
Version: 0.1.7
Summary: Client for Yahoo Finance data
License: MIT
License-File: LICENSE
Author: andrea
Author-email: vegavis@icloud.com
Requires-Python: >=3.10,<4.0
Classifier: License :: OSI Approved :: MIT License
Classifier: Programming Language :: Python :: 3
Classifier: Programming Language :: Python :: 3.10
Classifier: Programming Language :: Python :: 3.11
Classifier: Programming Language :: Python :: 3.12
Classifier: Programming Language :: Python :: 3.13
Classifier: Programming Language :: Python :: 3.14
Requires-Dist: curl-cffi (>=0.10.0,<0.11.0)
Requires-Dist: pandas (>=2.2.2,<3.0.0)
